magnus_extension_aws_config/aws.py
magnus_extension_aws_config-0.2.0.dist-info/WHEEL
magnus_extension_aws_config-0.2.0.dist-info/METADATA
magnus_extension_aws_config-0.2.0.dist-info/RECORD
