Metadata-Version: 2.1
Name: magnus-extension-aws-config
Version: 0.2.0
Summary: Magnus utility extension to provide AWS Configuration mixin
Home-page: https://github.com/AstraZeneca/magnus-extension
License: Apache-2.0
Author: Vijay Vammi
Author-email: vijay.vammi@astrazeneca.com
Requires-Python: >=3.8,<4.0
Classifier: License :: OSI Approved :: Apache Software License
Classifier: Programming Language :: Python :: 3
Classifier: Programming Language :: Python :: 3.8
Classifier: Programming Language :: Python :: 3.9
Classifier: Programming Language :: Python :: 3.10
Classifier: Programming Language :: Python :: 3.11
Requires-Dist: boto3
Requires-Dist: magnus (>=0.4.1,<0.5.0)
Requires-Dist: pydantic (>=1.10.4,<2.0.0)
Project-URL: Documentation, https://astrazeneca.github.io/magnus-extension/
Project-URL: Repository, https://github.com/AstraZeneca/magnus-extension
